grabba/__init__.py
grabba/api/__init__.py
grabba/api/client.py
grabba/api/utils.py
grabba/types/__init__.py
grabba/types/client_response_types.py
grabba/types/enums.py
grabba/types/job_navigation_types.py
grabba/types/job_schedule_types.py
grabba/types/job_task_types.py
grabba/types/job_types.py
grabba/types/knowledge_base_types.py
grabba-0.0.11.dist-info/LICENSE
grabba-0.0.11.dist-info/METADATA
grabba-0.0.11.dist-info/WHEEL
grabba-0.0.11.dist-info/RECORD
